rivescript/__init__.py
rivescript/__main__.py
rivescript/brain.py
rivescript/exceptions.py
rivescript/inheritance.py
rivescript/interactive.py
rivescript/parser.py
rivescript/python.py
rivescript/regexp.py
rivescript/rivescript.py
rivescript/sessions.py
rivescript/sorting.py
rivescript/utils.py
rivescript-1.15.0.dist-info/LICENSE
rivescript-1.15.0.dist-info/METADATA
rivescript-1.15.0.dist-info/WHEEL
rivescript-1.15.0.dist-info/top_level.txt
rivescript-1.15.0.dist-info/RECORD
