Metadata-Version: 1.1
Name: rivescript
Version: 1.15.0
Summary: A Chatterbot Scripting Language
Home-page: https://github.com/aichaos/rivescript-python
Author: Noah Petherbridge
Author-email: root@kirsle.net
License: MIT
Keywords: bot,chatbot,chatterbot,ai,aiml,chatscript,buddyscript
Platform: UNKNOWN
Classifier: License :: OSI Approved :: MIT License
Classifier: Programming Language :: Python
Classifier: Programming Language :: Python :: 2
Classifier: Programming Language :: Python :: 3
Classifier: Development Status :: 5 - Production/Stable
Classifier: Intended Audience :: Developers
Classifier: Topic :: Scientific/Engineering :: Artificial Intelligence
